pro/__init__.py
pro/pdf2image.py
pro/pdf2text.py
moshtrainpdf-1.0.dist-info/METADATA
moshtrainpdf-1.0.dist-info/WHEEL
moshtrainpdf-1.0.dist-info/top_level.txt
moshtrainpdf-1.0.dist-info/RECORD
