Metadata-Version: 2.1
Name: moshtrainpdf
Version: 1.0
Summary: This is my homepage
